sentry_dingtalk_xz/__init__.py
sentry_dingtalk_xz/forms.py
sentry_dingtalk_xz/plugin.py
sentry_dingtalk_xz-1.0.14.dist-info/LICENSE
sentry_dingtalk_xz-1.0.14.dist-info/METADATA
sentry_dingtalk_xz-1.0.14.dist-info/WHEEL
sentry_dingtalk_xz-1.0.14.dist-info/entry_points.txt
sentry_dingtalk_xz-1.0.14.dist-info/top_level.txt
sentry_dingtalk_xz-1.0.14.dist-info/RECORD
