Metadata-Version: 2.1
Name: sentry-dingtalk-xz
Version: 1.0.14
Summary: sentry extension which can send error to dingtalk.
Home-page: https://github.com/1018ji/sentry_dingtalk_xz
Author: 1018ji
Author-email: hyy126126@126.com
License: GNU
Keywords: sentry dingtalk xiaozhu
Platform: UNKNOWN
Classifier: Framework :: Django
Classifier: Intended Audience :: Developers
Classifier: Operating System :: OS Independent
Classifier: Natural Language :: Chinese (Simplified)
Classifier: Programming Language :: Python :: 2.7
Classifier: License :: OSI Approved :: GNU General Public License v3 (GPLv3)
Requires-Dist: sentry
Requires-Dist: requests
Requires-Dist: Django
